example_package_mustafa1sms2_3/__init__.py
example_package_mustafa1sms2_3/example.py
example_package_mustafa1sms2_3-0.0.2.dist-info/LICENSE.txt
example_package_mustafa1sms2_3-0.0.2.dist-info/METADATA
example_package_mustafa1sms2_3-0.0.2.dist-info/WHEEL
example_package_mustafa1sms2_3-0.0.2.dist-info/top_level.txt
example_package_mustafa1sms2_3-0.0.2.dist-info/RECORD
